ask_shell/__init__.py
ask_shell/__main__.py
ask_shell/ask.py
ask_shell/console.py
ask_shell/py.typed
ask_shell/settings.py
ask_shell/shell.py
ask_shell/shell_events.py
ask_shell/_internal/__init__.py
ask_shell/_internal/_run.py
ask_shell/_internal/_run_env.py
ask_shell/_internal/events.py
ask_shell/_internal/global_callbacks.py
ask_shell/_internal/interactive.py
ask_shell/_internal/models.py
ask_shell/_internal/rich_live.py
ask_shell/_internal/rich_live_callback.py
ask_shell/_internal/rich_progress.py
ask_shell/_internal/rich_run_state.py
ask_shell/_internal/run_pool.py
ask_shell/_internal/typer_command.py
ask_shell-0.3.1.dist-info/METADATA
ask_shell-0.3.1.dist-info/WHEEL
ask_shell-0.3.1.dist-info/licenses/LICENSE
ask_shell-0.3.1.dist-info/RECORD
