Metadata-Version: 2.4
Name: ask-shell
Version: 0.3.1
Summary: Build Pretty, Helpful, and Testable CLIs
Author-email: EspenAlbert <espen.albert1@gmail.com>
License-Expression: MIT
License-File: LICENSE
Classifier: Development Status :: 4 - Beta
Classifier: Programming Language :: Python :: 3.13
Classifier: Programming Language :: Python :: 3.14
Requires-Python: >=3.13
Requires-Dist: model-lib[toml]
Requires-Dist: questionary>=2.1.0
Requires-Dist: rich>=13.9.4
Requires-Dist: typer>=0.16.0
Requires-Dist: zero-3rdparty
